my_final_llm/__init__.py
my_final_llm/llm.py
my_final_llm-0.1.0.dist-info/LICENSE
my_final_llm-0.1.0.dist-info/METADATA
my_final_llm-0.1.0.dist-info/WHEEL
my_final_llm-0.1.0.dist-info/entry_points.txt
my_final_llm-0.1.0.dist-info/RECORD
