Metadata-Version: 2.1
Name: my-final-llm
Version: 0.1.0
Summary: looks good
Author: Amir
Author-email: amir.nagri@gmail.com
Requires-Python: >=3.8.1,<3.12
Classifier: Programming Language :: Python :: 3
Classifier: Programming Language :: Python :: 3.9
Classifier: Programming Language :: Python :: 3.10
Classifier: Programming Language :: Python :: 3.11
Requires-Dist: bodhisearch (>=0.1.0,<0.2.0)
